sasktran2-2026.2.0.dist-info/RECORD
sasktran2-2026.2.0.dist-info/WHEEL
sasktran2-2026.2.0.dist-info/METADATA
sasktran2/config.py
sasktran2/units.py
sasktran2/constants.py
sasktran2/appconfig.py
sasktran2/__init__.py
sasktran2/geodetic.py
sasktran2/engine.py
sasktran2/geometry.py
sasktran2/_core_rust.abi3.so
sasktran2/atmosphere.py
sasktran2/solar/__init__.py
sasktran2/solar/model.py
sasktran2/database/hitran.py
sasktran2/database/web.py
sasktran2/database/aer_line.py
sasktran2/database/__init__.py
sasktran2/database/hitran_line.py
sasktran2/database/base.py
sasktran2/database/mie.py
sasktran2/polarization/__init__.py
sasktran2/spectroscopy/__init__.py
sasktran2/util/interpolation.py
sasktran2/util/__init__.py
sasktran2/util/build_info.py
sasktran2/util/state.py
sasktran2/mie/refractive.py
sasktran2/mie/__init__.py
sasktran2/mie/distribution.py
sasktran2/mie/wrappers.py
sasktran2/.dylibs/libscipy_openblas64_.dylib
sasktran2/.dylibs/libomp.dylib
sasktran2/.dylibs/libgfortran.5.dylib
sasktran2/.dylibs/libquadmath.0.dylib
sasktran2/.dylibs/libgcc_s.1.1.dylib
sasktran2/legendre/__init__.py
sasktran2/optical/hitran.py
sasktran2/optical/database.py
sasktran2/optical/__init__.py
sasktran2/optical/quantities.py
sasktran2/optical/henyey.py
sasktran2/optical/rayleigh.py
sasktran2/optical/refraction.py
sasktran2/optical/base.py
sasktran2/optical/mie.py
sasktran2/optical/aerline.py
sasktran2/climatology/mipas.py
sasktran2/climatology/us76.py
sasktran2/climatology/__init__.py
sasktran2/climatology/glossac.py
sasktran2/test_util/scenarios.py
sasktran2/test_util/wf.py
sasktran2/test_util/__init__.py
sasktran2/constituent/collisioninducedabsorber.py
sasktran2/constituent/gaussianheight.py
sasktran2/constituent/amf.py
sasktran2/constituent/numdenscatterer.py
sasktran2/constituent/__init__.py
sasktran2/constituent/manual.py
sasktran2/constituent/numdenaltitudeabsorber.py
sasktran2/constituent/rayleigh.py
sasktran2/constituent/solar.py
sasktran2/constituent/vmraltitudeabsorber.py
sasktran2/constituent/base.py
