Metadata-Version: 2.4
Name: sasktran2
Version: 2026.2.0
Classifier: Development Status :: 4 - Beta
Classifier: License :: OSI Approved :: MIT License
Classifier: Programming Language :: Python :: 3 :: Only
Classifier: Programming Language :: Python :: 3.10
Classifier: Programming Language :: Python :: 3.11
Classifier: Programming Language :: Python :: 3.12
Classifier: Programming Language :: Python :: 3.13
Requires-Dist: numpy
Requires-Dist: appdirs
Requires-Dist: pyyaml
Requires-Dist: xarray>=2023.0.0
Requires-Dist: scipy
Requires-Dist: netcdf4
Requires-Dist: sasktran2[solar,hapi] ; extra == 'complete'
Requires-Dist: ruff ; extra == 'dev'
Requires-Dist: sphinx ; extra == 'dev'
Requires-Dist: sphinx-book-theme ; extra == 'dev'
Requires-Dist: myst-nb ; extra == 'dev'
Requires-Dist: sphinx-design ; extra == 'dev'
Requires-Dist: sphinx-github-changelog ; extra == 'dev'
Requires-Dist: sphinxcontrib-bibtex ; extra == 'dev'
Requires-Dist: hitran-api ; extra == 'hapi'
Requires-Dist: astropy ; extra == 'solar'
Requires-Dist: pytest ; extra == 'test'
Provides-Extra: complete
Provides-Extra: dev
Provides-Extra: hapi
Provides-Extra: solar
Provides-Extra: test
Summary: The SASKTRAN radiative transfer model Version 2
Author-email: Daniel Zawada <daniel.zawada@usask.ca>
License: MIT
Requires-Python: >=3.10
